technical_drawing_parser/__init__.py
technical_drawing_parser/datamodel/__init__.py
technical_drawing_parser/datamodel/base_model.py
technical_drawing_parser/datamodel/image_block.py
technical_drawing_parser/datamodel/uptool_image.py
technical_drawing_parser/llm_backends/__init__.py
technical_drawing_parser/llm_backends/llm_backend.py
technical_drawing_parser/llm_backends/backends/__init__.py
technical_drawing_parser/llm_backends/backends/openai_backend.py
technical_drawing_parser/pipeline/__init__.py
technical_drawing_parser/pipeline/image_pipeline.py
technical_drawing_parser/pipeline/llm_pipeline.py
technical_drawing_parser-0.0.1rc34.post1.dist-info/LICENSE
technical_drawing_parser-0.0.1rc34.post1.dist-info/WHEEL
technical_drawing_parser-0.0.1rc34.post1.dist-info/METADATA
technical_drawing_parser-0.0.1rc34.post1.dist-info/RECORD
