Metadata-Version: 2.3
Name: technical_drawing_parser
Version: 0.0.1rc34.post1
Summary: Python package for parsing technical drawings.
Author-email: Yang Shen <yang@uptool.com>
Requires-Python: >=3.8.1
Classifier: Development Status :: 3 - Alpha
Classifier: Intended Audience :: Developers
Classifier: License :: OSI Approved :: MIT License
Classifier: Programming Language :: Python :: 3 :: Only
Classifier: Programming Language :: Python :: 3.8
Classifier: Programming Language :: Python :: 3.9
Classifier: Programming Language :: Python :: 3.10
Classifier: Programming Language :: Python :: 3.11
Requires-Dist: pdf2image==1.17.0
Requires-Dist: pydantic==2.10.6
Requires-Dist: pytesseract==0.3.13
Requires-Dist: Rtree==1.3.0
Requires-Dist: openai==1.63.0
Requires-Dist: numpy==2.2.3
Requires-Dist: pypdf==5.3.0
Requires-Dist: opencv-contrib-python==4.10.0.84
Requires-Dist: opencv-stubs==0.0.10 ; extra == "dev"
Requires-Dist: pyspark>=3.0.0 ; extra == "spark"
Requires-Dist: bandit[toml]==1.7.5 ; extra == "test"
Requires-Dist: black==23.3.0 ; extra == "test"
Requires-Dist: check-manifest==0.50 ; extra == "test"
Requires-Dist: flake8-bugbear==24.12.12 ; extra == "test"
Requires-Dist: flake8-docstrings ; extra == "test"
Requires-Dist: flake8-formatter_junit_xml ; extra == "test"
Requires-Dist: flake8 ; extra == "test"
Requires-Dist: flake8-pyproject ; extra == "test"
Requires-Dist: pre-commit==4.1.0 ; extra == "test"
Requires-Dist: pylint==3.3.4 ; extra == "test"
Requires-Dist: pylint_junit ; extra == "test"
Requires-Dist: pytest-cov==6.0.0 ; extra == "test"
Requires-Dist: pytest-mock<3.10.1 ; extra == "test"
Requires-Dist: pytest-runner ; extra == "test"
Requires-Dist: pytest==8.3.4 ; extra == "test"
Requires-Dist: pytest-github-actions-annotate-failures ; extra == "test"
Requires-Dist: shellcheck-py==0.10.0.1 ; extra == "test"
Project-URL: Documentation, https://github.com/uptoolapp/technical_drawing_parser/tree/main#readme
Project-URL: Source, https://github.com/uptoolapp/technical_drawing_parser
Project-URL: Tracker, https://github.com/uptoolapp/technical_drawing_parser/issues
Provides-Extra: dev
Provides-Extra: spark
Provides-Extra: test
